LICENSE
MANIFEST.in
README.rst
setup.py
minetime/__init__.py
minetime/cli.py
minetime/helpers.py
minetime.egg-info/PKG-INFO
minetime.egg-info/SOURCES.txt
minetime.egg-info/dependency_links.txt
minetime.egg-info/entry_points.txt
minetime.egg-info/requires.txt
minetime.egg-info/top_level.txt
minetime_lib/__init__.py
minetime_lib/lib.py
minetime_lib/proxy.py