Metadata-Version: 1.0
Name: minetime
Version: 0.2.8
Summary: A simple Command line application helping you play with timelogs of configured redmine server.
Home-page: https://gitlab.com/yakoi/minetime
Author: yakoi
Author-email: jpgelinas@gmail.com
License:                     GNU GENERAL PUBLIC LICENSE
